{
  "project": "Nigeria Legal Marketplace MVP",
  "last_updated": "2026-04-20T23:59",
  "phases": [
    {
      "id": "phase-1",
      "name": "Core MVP API",
      "status": "in-progress",
      "features": [
        {
          "id": "feat-001",
          "name": "Problem-first intake endpoint",
          "status": "completed",
          "notes": "POST /api/intake/match implemented with category inference"
        },
        {
          "id": "feat-002",
          "name": "Balanced ranking engine",
          "status": "completed",
          "notes": "Weighted scoring + explainable reasons"
        },
        {
          "id": "feat-003",
          "name": "Adaptive exposure and new-lawyer rotation",
          "status": "completed",
          "notes": "Exposure bands 25/20/15/10 with eligibility gates"
        },
        {
          "id": "feat-004",
          "name": "Lawyer profile endpoint",
          "status": "completed",
          "notes": "GET /api/lawyers/{lawyer_id}"
        },
        {
          "id": "feat-005",
          "name": "Complaint/tier trigger workflows",
          "status": "completed",
          "notes": "Complaint filing and resolution triggers implemented"
        },
        {
          "id": "feat-006",
          "name": "Audit event logging",
          "status": "completed",
          "notes": "Sensitive actions now write to audit_events and admin feed"
        },
        {
          "id": "feat-007",
          "name": "In-app notifications",
          "status": "completed",
          "notes": "Notification creation, listing, and read state endpoint delivered"
        },
        {
          "id": "feat-008",
          "name": "Paystack-style payment simulation",
          "status": "completed",
          "notes": "Initialize + verify simulation flow with references and gateway statuses"
        }
      ],
      "tasks": [
        {
          "id": "task-001",
          "title": "Core API scaffolding",
          "status": "completed",
          "owner": "copilot",
          "updated_on": "2026-04-02"
        },
        {
          "id": "task-002",
          "title": "Add seed data and models",
          "status": "completed",
          "owner": "copilot",
          "updated_on": "2026-04-02"
        },
        {
          "id": "task-003",
          "title": "Tests for ranking and API",
          "status": "completed",
          "owner": "copilot",
          "updated_on": "2026-04-02"
        },
        {
          "id": "task-004",
          "title": "Persistence layer",
          "status": "completed",
          "owner": "unassigned",
          "updated_on": "2026-04-02",
          "notes": "SQLite persistence implemented"
        },
        {
          "id": "task-005",
          "title": "Implement complaint trigger matrix",
          "status": "completed",
          "owner": "copilot",
          "updated_on": "2026-04-02",
          "notes": "Complaint trigger workflows implemented"
        },
        {
          "id": "task-006",
          "title": "Implement auth and KYC endpoints",
          "status": "completed",
          "owner": "copilot",
          "updated_on": "2026-04-02",
          "notes": "Auth, role guards, and KYC endpoints delivered"
        },
        {
          "id": "task-007",
          "title": "Implement token expiry and refresh rotation",
          "status": "completed",
          "owner": "copilot",
          "updated_on": "2026-04-02",
          "notes": "Access/refresh expiry, rotation, and logout revocation implemented"
        },
        {
          "id": "task-008",
          "title": "Implement messaging, consultations, and payment simulation",
          "status": "completed",
          "owner": "copilot",
          "updated_on": "2026-04-02",
          "notes": "Chat, booking workflow, and simulated payment lifecycle delivered"
        },
        {
          "id": "task-009",
          "title": "Implement secure consultation document handling",
          "status": "completed",
          "owner": "copilot",
          "updated_on": "2026-04-02",
          "notes": "Authorized upload, list, and download flows added for consultation documents"
        },
        {
          "id": "task-010",
          "title": "Implement audit event tracking",
          "status": "completed",
          "owner": "copilot",
          "updated_on": "2026-04-02",
          "notes": "Audit persistence and admin audit feed endpoint delivered"
        },
        {
          "id": "task-011",
          "title": "Implement notifications",
          "status": "completed",
          "owner": "copilot",
          "updated_on": "2026-04-02",
          "notes": "In-app notifications wired for messaging, consultations, documents, and payments"
        },
        {
          "id": "task-012",
          "title": "Implement Paystack simulation flow",
          "status": "completed",
          "owner": "copilot",
          "updated_on": "2026-04-02",
          "notes": "Paystack-style initialize and verify simulation APIs added"
        },
        {
          "id": "task-013",
          "title": "Security and auth hardening",
          "status": "completed",
          "owner": "copilot",
          "updated_on": "2026-04-17",
          "notes": "Implemented PBKDF2 password hashing, lawyer_id mapping, complaint auth guards, and auth rate limiting."
        },
        {
          "id": "task-014",
          "title": "Pilot environment and backups",
          "status": "completed",
          "owner": "copilot",
          "updated_on": "2026-04-17",
          "notes": "Added .env baseline, backup script, and pilot auth recovery runbook."
        },
        {
          "id": "task-015",
          "title": "Observability baseline setup",
          "status": "completed",
          "owner": "copilot",
          "updated_on": "2026-04-17",
          "notes": "Added request/error structured logging, request IDs, latency thresholding, and pilot alert checklist."
        },
        {
          "id": "task-016",
          "title": "Deployment and rollback pipeline",
          "status": "completed",
          "owner": "copilot",
          "updated_on": "2026-04-17",
          "notes": "Added deployment runbook, rollback checklist, smoke test script, and requirements cleanup."
        },
        {
          "id": "task-017",
          "title": "End-to-end UAT automation",
          "status": "completed",
          "owner": "copilot",
          "updated_on": "2026-04-17",
          "notes": "Added UAT runner script, scenario docs, and validated workflow-heavy test suites."
        }
      ]
    },
    {
      "id": "phase-2",
      "name": "NDPA Compliance & Data Governance",
      "status": "in-progress",
      "features": [
        {
          "id": "feat-101",
          "name": "Breach notification SLA tracking",
          "status": "completed",
          "notes": "72-hour NDPA deadline calculation, status monitoring, and admin escalation"
        },
        {
          "id": "feat-102",
          "name": "Annual Stamp & Seal compliance badge",
          "status": "completed",
          "notes": "Encrypted seal file upload (Fernet at-rest), public trust badge in search/ranking, lawyer upload UI, admin audit/download endpoint"
        }
      ],
      "tasks": [
        {
          "id": "task-018",
          "title": "Implement breach notification SLA tracking",
          "status": "completed",
          "owner": "copilot",
          "updated_on": "2026-04-20",
          "notes": "Added SLA deadline fields (notification_deadline, escalation_triggered, escalation_triggered_at) to breach_incidents table via migration 20260420_0004. Extended BreachIncidentResponse and BreachSlaStatusResponse models with SLA fields. Implemented DB functions: check_breach_sla_status (deadline calculation), list_breach_incidents_by_sla_status (filtering by SLA status), trigger_breach_escalation (admin alert escalation). Added API endpoints: GET /api/compliance/breach-incidents/sla-status (list breaches by deadline urgency), POST /api/compliance/breach-incidents/{id}/escalate (admin-only escalation trigger). Full test coverage with test_breach_sla_tracking, test_breach_escalation_admin_only, test_breach_sla_filter_by_status. All 46 tests passing (43 baseline + 3 new SLA tests). Fixed datetime type handling and audit event function signature issues."
        },
        {
          "id": "task-019",
          "title": "Annual stamp & seal schema and API layer",
          "status": "completed",
          "owner": "copilot",
          "updated_on": "2026-04-20",
          "notes": "Created migration 20260420_0005 adding lawyer_practice_seals and seal_events tables. Added seal CRUD and listing DB functions. Added POST /api/compliance/practice-seal/upload, GET /api/compliance/practice-seal/check, GET /api/compliance/practice-seal/{lawyer_id}, GET /api/compliance/practising-list, POST /api/compliance/practice-seal/{lawyer_id}/verify, GET /api/compliance/practice-seal/{lawyer_id}/audit-trail. Wired malware scanning on seal upload."
        },
        {
          "id": "task-020",
          "title": "Seal trust badge in ranking and search",
          "status": "completed",
          "owner": "copilot",
          "updated_on": "2026-04-20",
          "notes": "Added CPD-compliant seal trust bonus to ranking engine. Appended 'Seal & Stamp {year}' badge to compliant lawyer profiles. Updated frontend search page to render seal icon when badge is present."
        },
        {
          "id": "task-021",
          "title": "Lawyer seal upload UI and encryption at rest",
          "status": "completed",
          "owner": "copilot",
          "updated_on": "2026-04-20",
          "notes": "Added cryptography==42.0.8 dependency. Added encrypt_seal_bytes/decrypt_seal_bytes Fernet helpers and SealEncryptionError in app/security.py. Added SEAL_ENCRYPTION_KEY config in app/settings.py with fallback derivation. Updated upload endpoint to encrypt file bytes before writing to disk. Added frontend lawyer seal upload page at /lawyer/seal. Added Seal nav entry in Navigation.js and dashboard shortcut card. Added .env.example entry for SEAL_ENCRYPTION_KEY."
        },
        {
          "id": "task-022",
          "title": "Admin seal document download endpoint and tests",
          "status": "completed",
          "owner": "copilot",
          "updated_on": "2026-04-20",
          "notes": "Added admin-only GET /api/compliance/practice-seal/{lawyer_id}/document/download endpoint. Decrypts stored Fernet bytes and streams original file to admin with correct content-type and Content-Disposition headers. Logs audit event on every download. Added test_admin_can_download_decrypted_seal_document and test_non_admin_cannot_download_seal_document. Full suite: 23/23 tests passing (compliance 19, ranking 4)."
        }
      ]
    }
  ],
  "continuity": {
    "project_context": "Nigeria-first legal marketplace MVP focused on trust, verification, and explainable problem-first matching.",
    "timeline": [
      {
        "date": "2026-04-02",
        "type": "milestone",
        "summary": "Initialized FastAPI MVP with intake match and profile endpoints",
        "refs": [
          "task-001",
          "feat-001",
          "feat-004"
        ]
      },
      {
        "date": "2026-04-02",
        "type": "milestone",
        "summary": "Implemented balanced ranking with adaptive exposure bands and explainable reasons",
        "refs": [
          "task-003",
          "feat-002",
          "feat-003"
        ]
      },
      {
        "date": "2026-04-02",
        "type": "testing",
        "summary": "Baseline test suite passing",
        "refs": [
          "tests/test_api.py",
          "tests/test_ranking.py"
        ]
      },
      {
        "date": "2026-04-02",
        "type": "note",
        "summary": "Validated continuity tracker workflow",
        "refs": [
          "task-005"
        ]
      },
      {
        "date": "2026-04-02",
        "type": "decision",
        "summary": "Tracker continuity: Use timeline + decisions + handoff commands",
        "refs": []
      },
      {
        "date": "2026-04-02",
        "type": "status_change",
        "summary": "task-004 -> completed",
        "refs": [
          "task-004"
        ]
      },
      {
        "date": "2026-04-02",
        "type": "status_change",
        "summary": "task-005 -> completed",
        "refs": [
          "task-005"
        ]
      },
      {
        "date": "2026-04-02",
        "type": "note",
        "summary": "Phase-2 delivered: persistence + complaint APIs + tests",
        "refs": [
          "task-004",
          "task-005",
          "feat-005"
        ]
      },
      {
        "date": "2026-04-02",
        "type": "task_added",
        "summary": "Added task-006: Implement auth and KYC endpoints",
        "refs": [
          "task-006",
          "phase-1"
        ]
      },
      {
        "date": "2026-04-02",
        "type": "status_change",
        "summary": "task-006 -> completed",
        "refs": [
          "task-006"
        ]
      },
      {
        "date": "2026-04-02",
        "type": "note",
        "summary": "Phase-3 delivered: auth + KYC + tracker API",
        "refs": [
          "task-006"
        ]
      },
      {
        "date": "2026-04-02",
        "type": "note",
        "summary": "Migrated FastAPI startup to lifespan handler; removed on_event deprecation path",
        "refs": [
          "app/main.py"
        ]
      },
      {
        "date": "2026-04-02",
        "type": "task_added",
        "summary": "Added task-007: Implement token expiry and refresh rotation",
        "refs": [
          "task-007",
          "phase-1"
        ]
      },
      {
        "date": "2026-04-02",
        "type": "status_change",
        "summary": "task-007 -> completed",
        "refs": [
          "task-007"
        ]
      },
      {
        "date": "2026-04-02",
        "type": "decision",
        "summary": "Session security model: Use short-lived access tokens and rotating refresh tokens",
        "refs": []
      },
      {
        "date": "2026-04-02",
        "type": "task_added",
        "summary": "Added task-008: Implement messaging, consultations, and payment simulation",
        "refs": [
          "task-008",
          "phase-1"
        ]
      },
      {
        "date": "2026-04-02",
        "type": "status_change",
        "summary": "task-008 -> completed",
        "refs": [
          "task-008"
        ]
      },
      {
        "date": "2026-04-02",
        "type": "note",
        "summary": "Delivered messaging + consultation booking + payment simulation APIs",
        "refs": [
          "task-008"
        ]
      },
      {
        "date": "2026-04-02",
        "type": "task_added",
        "summary": "Added task-009: Implement secure consultation document handling",
        "refs": [
          "task-009",
          "phase-1"
        ]
      },
      {
        "date": "2026-04-02",
        "type": "status_change",
        "summary": "task-009 -> completed",
        "refs": [
          "task-009"
        ]
      },
      {
        "date": "2026-04-02",
        "type": "note",
        "summary": "Delivered secure consultation document upload, listing, and download APIs",
        "refs": [
          "task-009",
          "tests/test_workflows.py"
        ]
      },
      {
        "date": "2026-04-02",
        "type": "task_added",
        "summary": "Added task-010: Implement audit event tracking",
        "refs": [
          "task-010",
          "phase-1"
        ]
      },
      {
        "date": "2026-04-02",
        "type": "status_change",
        "summary": "task-010 -> completed",
        "refs": [
          "task-010",
          "feat-006"
        ]
      },
      {
        "date": "2026-04-02",
        "type": "task_added",
        "summary": "Added task-011: Implement notifications",
        "refs": [
          "task-011",
          "phase-1"
        ]
      },
      {
        "date": "2026-04-02",
        "type": "status_change",
        "summary": "task-011 -> completed",
        "refs": [
          "task-011",
          "feat-007"
        ]
      },
      {
        "date": "2026-04-02",
        "type": "task_added",
        "summary": "Added task-012: Implement Paystack simulation flow",
        "refs": [
          "task-012",
          "phase-1"
        ]
      },
      {
        "date": "2026-04-02",
        "type": "status_change",
        "summary": "task-012 -> completed",
        "refs": [
          "task-012",
          "feat-008"
        ]
      },
      {
        "date": "2026-04-02",
        "type": "testing",
        "summary": "Full suite passed after audit, notifications, and Paystack simulation updates",
        "refs": [
          "tests/test_audit_notifications.py",
          "tests/test_workflows.py"
        ]
      },
      {
        "date": "2026-04-17",
        "type": "task_added",
        "summary": "Added task-013: Security and auth hardening",
        "refs": [
          "task-013",
          "phase-1"
        ]
      },
      {
        "date": "2026-04-17",
        "type": "task_added",
        "summary": "Added task-014: Pilot environment and backups",
        "refs": [
          "task-014",
          "phase-1"
        ]
      },
      {
        "date": "2026-04-17",
        "type": "task_added",
        "summary": "Added task-015: Observability baseline setup",
        "refs": [
          "task-015",
          "phase-1"
        ]
      },
      {
        "date": "2026-04-17",
        "type": "task_added",
        "summary": "Added task-016: Deployment and rollback pipeline",
        "refs": [
          "task-016",
          "phase-1"
        ]
      },
      {
        "date": "2026-04-17",
        "type": "task_added",
        "summary": "Added task-017: End-to-end UAT automation",
        "refs": [
          "task-017",
          "phase-1"
        ]
      },
      {
        "date": "2026-04-17",
        "type": "status_change",
        "summary": "task-013 -> completed",
        "refs": [
          "task-013"
        ]
      },
      {
        "date": "2026-04-17",
        "type": "status_change",
        "summary": "task-014 -> completed",
        "refs": [
          "task-014"
        ]
      },
      {
        "date": "2026-04-17",
        "type": "status_change",
        "summary": "task-015 -> completed",
        "refs": [
          "task-015"
        ]
      },
      {
        "date": "2026-04-17",
        "type": "status_change",
        "summary": "task-016 -> completed",
        "refs": [
          "task-016"
        ]
      },
      {
        "date": "2026-04-17",
        "type": "status_change",
        "summary": "task-017 -> completed",
        "refs": [
          "task-017"
        ]
      },
      {
        "date": "2026-04-17",
        "type": "decision",
        "summary": "Pilot database strategy: Use SQLite for pilot while preparing PostgreSQL migration readiness before scale-out.",
        "refs": []
      },
      {
        "date": "2026-04-17",
        "type": "note",
        "summary": "Completed pilot readiness tranche: security hardening, observability, deployment pipeline, and UAT automation",
        "refs": [
          "task-013",
          "task-014",
          "task-015",
          "task-016",
          "task-017"
        ]
      },
      {
        "date": "2026-04-17",
        "type": "note",
        "summary": "Implementation log entry added: Tracker command validation",
        "refs": [
          "task-017"
        ]
      },
      {
        "date": "2026-04-20",
        "type": "phase_opened",
        "summary": "Phase-2: NDPA Compliance & Data Governance",
        "refs": [
          "phase-2"
        ]
      },
      {
        "date": "2026-04-20",
        "type": "task_added",
        "summary": "Added task-018: Implement breach notification SLA tracking",
        "refs": [
          "task-018",
          "phase-2",
          "feat-101"
        ]
      },
      {
        "date": "2026-04-20",
        "type": "database_migration",
        "summary": "Created and applied migration 20260420_0004: Added SLA deadline tracking to breach_incidents (notification_deadline, escalation_triggered, escalation_triggered_at columns with index)",
        "refs": [
          "task-018"
        ]
      },
      {
        "date": "2026-04-20",
        "type": "feature_development",
        "summary": "Implemented SLA deadline calculation: NDPA requires 72-hour notification to NDPC from breach discovery",
        "refs": [
          "task-018",
          "feat-101"
        ]
      },
      {
        "date": "2026-04-20",
        "type": "api_endpoint_added",
        "summary": "Added GET /api/compliance/breach-incidents/sla-status: Lists breach incidents ordered by deadline urgency with filtering (on-track, at-risk, overdue, notified)",
        "refs": [
          "task-018"
        ]
      },
      {
        "date": "2026-04-20",
        "type": "api_endpoint_added",
        "summary": "Added POST /api/compliance/breach-incidents/{id}/escalate: Admin-only endpoint to trigger SLA escalation alerts",
        "refs": [
          "task-018"
        ]
      },
      {
        "date": "2026-04-20",
        "type": "testing",
        "summary": "Added 3 new SLA compliance tests: test_breach_sla_tracking, test_breach_escalation_admin_only, test_breach_sla_filter_by_status",
        "refs": [
          "task-018"
        ]
      },
      {
        "date": "2026-04-20",
        "type": "bug_fixed",
        "summary": "Fixed datetime type handling in SLA list function and audit event function signature mismatch",
        "refs": [
          "task-018"
        ]
      },
      {
        "date": "2026-04-20",
        "type": "status_change",
        "summary": "task-018 -> completed",
        "refs": [
          "task-018",
          "feat-101"
        ]
      },
      {
        "date": "2026-04-20",
        "type": "testing",
        "summary": "Full test suite validation: 46/46 tests passing (43 baseline + 3 new SLA tests). No regressions. SLA tracking feature production-ready.",
        "refs": [
          "task-018",
          "phase-2"
        ]
      },
      {
        "date": "2026-04-20",
        "type": "feature_development",
        "summary": "Started Annual Stamp & Seal compliance feature: schema, API layer, malware scan on upload",
        "refs": ["task-019", "feat-102"]
      },
      {
        "date": "2026-04-20",
        "type": "database_migration",
        "summary": "Created and applied migration 20260420_0005: Added lawyer_practice_seals and seal_events tables",
        "refs": ["task-019"]
      },
      {
        "date": "2026-04-20",
        "type": "api_endpoint_added",
        "summary": "Added 6 seal compliance endpoints: upload, check, get, practising-list, verify, audit-trail",
        "refs": ["task-019"]
      },
      {
        "date": "2026-04-20",
        "type": "feature_development",
        "summary": "Integrated Stamp & Seal trust badge into ranking engine and search results display",
        "refs": ["task-020", "feat-102"]
      },
      {
        "date": "2026-04-20",
        "type": "security",
        "summary": "Implemented Fernet encryption-at-rest for seal document files. Added SEAL_ENCRYPTION_KEY config. Seal bytes are encrypted on upload and never stored in plaintext.",
        "refs": ["task-021"]
      },
      {
        "date": "2026-04-20",
        "type": "feature_development",
        "summary": "Added lawyer-facing seal upload page (/lawyer/seal), Navigation.js entry, and dashboard shortcut card",
        "refs": ["task-021"]
      },
      {
        "date": "2026-04-20",
        "type": "api_endpoint_added",
        "summary": "Added admin-only GET /api/compliance/practice-seal/{lawyer_id}/document/download: decrypts and streams original seal file with audit logging",
        "refs": ["task-022"]
      },
      {
        "date": "2026-04-20",
        "type": "testing",
        "summary": "Added seal encryption-at-rest test and admin download tests. Full suite: 23/23 passing (compliance 19, ranking 4). No regressions.",
        "refs": ["task-019", "task-020", "task-021", "task-022", "feat-102"]
      },
      {
        "date": "2026-04-20",
        "type": "status_change",
        "summary": "task-019, task-020, task-021, task-022 -> completed; feat-102 -> completed",
        "refs": ["task-019", "task-020", "task-021", "task-022", "feat-102"]
      }
    ],
    "decisions": [
      {
        "date": "2026-04-02",
        "title": "Core matching approach",
        "context": "User selected Option B and requested Nigeria-native trust architecture.",
        "decision": "Use problem-first intake with balanced ranking and explainability.",
        "impact": "Improves onboarding clarity and trust for first-time legal users.",
        "owner": "product"
      },
      {
        "date": "2026-04-02",
        "title": "Fairness policy",
        "context": "Need new-lawyer discovery without degrading trust.",
        "decision": "Use quota rotation with adaptive exposure bands and strict eligibility gates.",
        "impact": "Maintains quality while preventing incumbent lock-in.",
        "owner": "product"
      },
      {
        "date": "2026-04-02",
        "title": "Tracker continuity",
        "context": "Need continuity across sessions",
        "decision": "Use timeline + decisions + handoff commands",
        "impact": "Faster re-entry and less context loss",
        "owner": "copilot"
      },
      {
        "date": "2026-04-02",
        "title": "Session security model",
        "context": "Legal app needs continuous UX with strong security",
        "decision": "Use short-lived access tokens and rotating refresh tokens",
        "impact": "Seamless conversations with safer session handling",
        "owner": "product"
      },
      {
        "date": "2026-04-17",
        "title": "Pilot database strategy",
        "context": "Need speed for first-wave validation with low operational overhead.",
        "decision": "Use SQLite for pilot while preparing PostgreSQL migration readiness before scale-out.",
        "impact": "Faster pilot launch with controlled migration risk.",
        "owner": "product"
      }
    ],
    "assumptions": [
      "Client identity uses NIN-only for low-friction onboarding.",
      "Lawyer trust layer uses NIN + NBA; BVN supports payout workflows.",
      "Escrow and payment protection workflows are phase-2 implementation."
    ],
    "next_focus": [
      "Integrate real Paystack APIs and webhook signature verification.",
      "Add out-of-band delivery channels (email/SMS) for notifications.",
      "Ship frontend workflows for notifications, payments, and document management.",
      "Add admin UI action to trigger seal document download from dashboard.",
      "Extend seal badge to lawyer public profile page.",
      "Automate SEAL_ENCRYPTION_KEY rotation with re-encryption script."
    ]
  }
}
